[
  {
    "question": "Where is the ICC headquarters located?",
    "options": ["Melbourne", "Dubai", "London", "Mumbai"],
    "answer": "Dubai"
  },
  {
    "question": "Which player has taken the most Test wickets?",
    "options": [
      "Shane Warne",
      "Anil Kumble",
      "James Anderson",
      "Muttiah Muralitharan"
    ],
    "answer": "Muttiah Muralitharan"
  },
  {
    "question": "What shape is a cricket ball?",
    "options": ["Cylindrical", "Round", "Square", "Oval"],
    "answer": "Round"
  },
  {
    "question": "Who holds the record for the highest individual ODI score?",
    "options": [
      "Rohit Sharma",
      "Virender Sehwag",
      "Martin Guptill",
      "Chris Gayle"
    ],
    "answer": "Rohit Sharma"
  },
  {
    "question": "Which country won the first Cricket World Cup?",
    "options": ["England", "India", "Australia", "West Indies"],
    "answer": "West Indies"
  },
  {
    "question": "Who holds the record for the highest individual ODI score?",
    "options": [
      "Martin Guptill",
      "Rohit Sharma",
      "Virender Sehwag",
      "Chris Gayle"
    ],
    "answer": "Rohit Sharma"
  },
  {
    "question": "Where is the ICC headquarters located?",
    "options": ["Mumbai", "Melbourne", "London", "Dubai"],
    "answer": "Dubai"
  },
  {
    "question": "What shape is a cricket ball?",
    "options": ["Round", "Oval", "Cylindrical", "Square"],
    "answer": "Round"
  },
  {
    "question": "Which country won the first Cricket World Cup?",
    "options": ["Australia", "West Indies", "England", "India"],
    "answer": "West Indies"
  },
  {
    "question": "Where is the ICC headquarters located?",
    "options": ["Mumbai", "Dubai", "Melbourne", "London"],
    "answer": "Dubai"
  },
  {
    "question": "Who holds the record for the highest individual ODI score?",
    "options": [
      "Chris Gayle",
      "Martin Guptill",
      "Virender Sehwag",
      "Rohit Sharma"
    ],
    "answer": "Rohit Sharma"
  },
  {
    "question": "Where is the ICC headquarters located?",
    "options": ["Dubai", "Mumbai", "Melbourne", "London"],
    "answer": "Dubai"
  },
  {
    "question": "Where is the ICC headquarters located?",
    "options": ["London", "Dubai", "Melbourne", "Mumbai"],
    "answer": "Dubai"
  },
  {
    "question": "Which player has taken the most Test wickets?",
    "options": [
      "Anil Kumble",
      "James Anderson",
      "Shane Warne",
      "Muttiah Muralitharan"
    ],
    "answer": "Muttiah Muralitharan"
  },
  {
    "question": "Which country won the first Cricket World Cup?",
    "options": ["West Indies", "India", "Australia", "England"],
    "answer": "West Indies"
  },
  {
    "question": "Which player has taken the most Test wickets?",
    "options": [
      "James Anderson",
      "Muttiah Muralitharan",
      "Anil Kumble",
      "Shane Warne"
    ],
    "answer": "Muttiah Muralitharan"
  },
  {
    "question": "Who holds the record for the highest individual ODI score?",
    "options": [
      "Chris Gayle",
      "Martin Guptill",
      "Virender Sehwag",
      "Rohit Sharma"
    ],
    "answer": "Rohit Sharma"
  },
  {
    "question": "Who holds the record for the highest individual ODI score?",
    "options": [
      "Rohit Sharma",
      "Virender Sehwag",
      "Martin Guptill",
      "Chris Gayle"
    ],
    "answer": "Rohit Sharma"
  },
  {
    "question": "Where is the ICC headquarters located?",
    "options": ["Dubai", "London", "Melbourne", "Mumbai"],
    "answer": "Dubai"
  },
  {
    "question": "What shape is a cricket ball?",
    "options": ["Cylindrical", "Round", "Oval", "Square"],
    "answer": "Round"
  },
  {
    "question": "What shape is a cricket ball?",
    "options": ["Round", "Cylindrical", "Oval", "Square"],
    "answer": "Round"
  },
  {
    "question": "Where is the ICC headquarters located?",
    "options": ["London", "Mumbai", "Melbourne", "Dubai"],
    "answer": "Dubai"
  },
  {
    "question": "What shape is a cricket ball?",
    "options": ["Cylindrical", "Round", "Oval", "Square"],
    "answer": "Round"
  },
  {
    "question": "Where is the ICC headquarters located?",
    "options": ["Dubai", "Mumbai", "Melbourne", "London"],
    "answer": "Dubai"
  },
  {
    "question": "Who holds the record for the highest individual ODI score?",
    "options": [
      "Martin Guptill",
      "Chris Gayle",
      "Rohit Sharma",
      "Virender Sehwag"
    ],
    "answer": "Rohit Sharma"
  },
  {
    "question": "What shape is a cricket ball?",
    "options": ["Round", "Cylindrical", "Square", "Oval"],
    "answer": "Round"
  },
  {
    "question": "Which player has taken the most Test wickets?",
    "options": [
      "Muttiah Muralitharan",
      "James Anderson",
      "Anil Kumble",
      "Shane Warne"
    ],
    "answer": "Muttiah Muralitharan"
  },
  {
    "question": "Which country won the first Cricket World Cup?",
    "options": ["England", "West Indies", "Australia", "India"],
    "answer": "West Indies"
  },
  {
    "question": "Which player has taken the most Test wickets?",
    "options": [
      "James Anderson",
      "Shane Warne",
      "Muttiah Muralitharan",
      "Anil Kumble"
    ],
    "answer": "Muttiah Muralitharan"
  },
  {
    "question": "Which player has taken the most Test wickets?",
    "options": [
      "James Anderson",
      "Shane Warne",
      "Muttiah Muralitharan",
      "Anil Kumble"
    ],
    "answer": "Muttiah Muralitharan"
  },
  {
    "question": "What shape is a cricket ball?",
    "options": ["Cylindrical", "Square", "Round", "Oval"],
    "answer": "Round"
  },
  {
    "question": "Which country won the first Cricket World Cup?",
    "options": ["England", "West Indies", "India", "Australia"],
    "answer": "West Indies"
  },
  {
    "question": "Which player has taken the most Test wickets?",
    "options": [
      "James Anderson",
      "Muttiah Muralitharan",
      "Shane Warne",
      "Anil Kumble"
    ],
    "answer": "Muttiah Muralitharan"
  },
  {
    "question": "Where is the ICC headquarters located?",
    "options": ["Mumbai", "London", "Dubai", "Melbourne"],
    "answer": "Dubai"
  },
  {
    "question": "Which country won the first Cricket World Cup?",
    "options": ["West Indies", "England", "Australia", "India"],
    "answer": "West Indies"
  },
  {
    "question": "What shape is a cricket ball?",
    "options": ["Cylindrical", "Square", "Oval", "Round"],
    "answer": "Round"
  },
  {
    "question": "Who holds the record for the highest individual ODI score?",
    "options": [
      "Chris Gayle",
      "Rohit Sharma",
      "Virender Sehwag",
      "Martin Guptill"
    ],
    "answer": "Rohit Sharma"
  },
  {
    "question": "Who holds the record for the highest individual ODI score?",
    "options": [
      "Chris Gayle",
      "Martin Guptill",
      "Virender Sehwag",
      "Rohit Sharma"
    ],
    "answer": "Rohit Sharma"
  },
  {
    "question": "What shape is a cricket ball?",
    "options": ["Round", "Cylindrical", "Square", "Oval"],
    "answer": "Round"
  },
  {
    "question": "Where is the ICC headquarters located?",
    "options": ["Melbourne", "Dubai", "Mumbai", "London"],
    "answer": "Dubai"
  },
  {
    "question": "Which country won the first Cricket World Cup?",
    "options": ["Australia", "India", "England", "West Indies"],
    "answer": "West Indies"
  },
  {
    "question": "Where is the ICC headquarters located?",
    "options": ["Mumbai", "London", "Melbourne", "Dubai"],
    "answer": "Dubai"
  },
  {
    "question": "What shape is a cricket ball?",
    "options": ["Square", "Oval", "Round", "Cylindrical"],
    "answer": "Round"
  },
  {
    "question": "Who holds the record for the highest individual ODI score?",
    "options": [
      "Rohit Sharma",
      "Martin Guptill",
      "Chris Gayle",
      "Virender Sehwag"
    ],
    "answer": "Rohit Sharma"
  },
  {
    "question": "Who holds the record for the highest individual ODI score?",
    "options": [
      "Chris Gayle",
      "Virender Sehwag",
      "Martin Guptill",
      "Rohit Sharma"
    ],
    "answer": "Rohit Sharma"
  },
  {
    "question": "What shape is a cricket ball?",
    "options": ["Round", "Square", "Oval", "Cylindrical"],
    "answer": "Round"
  },
  {
    "question": "Who holds the record for the highest individual ODI score?",
    "options": [
      "Chris Gayle",
      "Rohit Sharma",
      "Martin Guptill",
      "Virender Sehwag"
    ],
    "answer": "Rohit Sharma"
  },
  {
    "question": "Who holds the record for the highest individual ODI score?",
    "options": [
      "Chris Gayle",
      "Martin Guptill",
      "Virender Sehwag",
      "Rohit Sharma"
    ],
    "answer": "Rohit Sharma"
  },
  {
    "question": "Which country won the first Cricket World Cup?",
    "options": ["Australia", "West Indies", "India", "England"],
    "answer": "West Indies"
  },
  {
    "question": "Who holds the record for the highest individual ODI score?",
    "options": [
      "Chris Gayle",
      "Martin Guptill",
      "Rohit Sharma",
      "Virender Sehwag"
    ],
    "answer": "Rohit Sharma"
  },
  {
    "question": "Where is the ICC headquarters located?",
    "options": ["Mumbai", "Dubai", "London", "Melbourne"],
    "answer": "Dubai"
  },
  {
    "question": "Where is the ICC headquarters located?",
    "options": ["Melbourne", "Mumbai", "London", "Dubai"],
    "answer": "Dubai"
  },
  {
    "question": "What shape is a cricket ball?",
    "options": ["Square", "Oval", "Cylindrical", "Round"],
    "answer": "Round"
  },
  {
    "question": "What is the length of a cricket pitch?",
    "options": ["20 yards", "22 yards", "25 yards", "18 yards"],
    "answer": "22 yards"
  },
  {
    "question": "Who holds the record for the highest individual ODI score?",
    "options": [
      "Rohit Sharma",
      "Martin Guptill",
      "Virender Sehwag",
      "Chris Gayle"
    ],
    "answer": "Rohit Sharma"
  },
  {
    "question": "Where is the ICC headquarters located?",
    "options": ["Melbourne", "London", "Mumbai", "Dubai"],
    "answer": "Dubai"
  },
  {
    "question": "What shape is a cricket ball?",
    "options": ["Round", "Cylindrical", "Square", "Oval"],
    "answer": "Round"
  },
  {
    "question": "Who holds the record for the highest individual ODI score?",
    "options": [
      "Chris Gayle",
      "Rohit Sharma",
      "Virender Sehwag",
      "Martin Guptill"
    ],
    "answer": "Rohit Sharma"
  },
  {
    "question": "Which country won the first Cricket World Cup?",
    "options": ["England", "West Indies", "Australia", "India"],
    "answer": "West Indies"
  },
  {
    "question": "Which player has taken the most Test wickets?",
    "options": [
      "Shane Warne",
      "Anil Kumble",
      "Muttiah Muralitharan",
      "James Anderson"
    ],
    "answer": "Muttiah Muralitharan"
  },
  {
    "question": "Who holds the record for the highest individual ODI score?",
    "options": [
      "Virender Sehwag",
      "Chris Gayle",
      "Rohit Sharma",
      "Martin Guptill"
    ],
    "answer": "Rohit Sharma"
  },
  {
    "question": "Where is the ICC headquarters located?",
    "options": ["Mumbai", "Dubai", "Melbourne", "London"],
    "answer": "Dubai"
  },
  {
    "question": "Which country won the first Cricket World Cup?",
    "options": ["India", "England", "West Indies", "Australia"],
    "answer": "West Indies"
  },
  {
    "question": "Which country won the first Cricket World Cup?",
    "options": ["West Indies", "Australia", "England", "India"],
    "answer": "West Indies"
  },
  {
    "question": "Where is the ICC headquarters located?",
    "options": ["Dubai", "London", "Mumbai", "Melbourne"],
    "answer": "Dubai"
  },
  {
    "question": "Which player has taken the most Test wickets?",
    "options": [
      "James Anderson",
      "Muttiah Muralitharan",
      "Shane Warne",
      "Anil Kumble"
    ],
    "answer": "Muttiah Muralitharan"
  },
  {
    "question": "Where is the ICC headquarters located?",
    "options": ["Dubai", "Mumbai", "Melbourne", "London"],
    "answer": "Dubai"
  },
  {
    "question": "Which country won the first Cricket World Cup?",
    "options": ["Australia", "England", "India", "West Indies"],
    "answer": "West Indies"
  },
  {
    "question": "What shape is a cricket ball?",
    "options": ["Round", "Cylindrical", "Square", "Oval"],
    "answer": "Round"
  },
  {
    "question": "What shape is a cricket ball?",
    "options": ["Cylindrical", "Square", "Round", "Oval"],
    "answer": "Round"
  },
  {
    "question": "Who holds the record for the highest individual ODI score?",
    "options": [
      "Chris Gayle",
      "Virender Sehwag",
      "Martin Guptill",
      "Rohit Sharma"
    ],
    "answer": "Rohit Sharma"
  },
  {
    "question": "Where is the ICC headquarters located?",
    "options": ["Dubai", "London", "Mumbai", "Melbourne"],
    "answer": "Dubai"
  },
  {
    "question": "What shape is a cricket ball?",
    "options": ["Round", "Cylindrical", "Square", "Oval"],
    "answer": "Round"
  },
  {
    "question": "What shape is a cricket ball?",
    "options": ["Square", "Round", "Oval", "Cylindrical"],
    "answer": "Round"
  },
  {
    "question": "Who holds the record for the highest individual ODI score?",
    "options": [
      "Chris Gayle",
      "Rohit Sharma",
      "Virender Sehwag",
      "Martin Guptill"
    ],
    "answer": "Rohit Sharma"
  },
  {
    "question": "What shape is a cricket ball?",
    "options": ["Oval", "Square", "Round", "Cylindrical"],
    "answer": "Round"
  },
  {
    "question": "Where is the ICC headquarters located?",
    "options": ["Melbourne", "Mumbai", "London", "Dubai"],
    "answer": "Dubai"
  },
  {
    "question": "Who holds the record for the highest individual ODI score?",
    "options": [
      "Virender Sehwag",
      "Chris Gayle",
      "Martin Guptill",
      "Rohit Sharma"
    ],
    "answer": "Rohit Sharma"
  },
  {
    "question": "Which player has taken the most Test wickets?",
    "options": [
      "James Anderson",
      "Muttiah Muralitharan",
      "Anil Kumble",
      "Shane Warne"
    ],
    "answer": "Muttiah Muralitharan"
  },
  {
    "question": "Where is the ICC headquarters located?",
    "options": ["Melbourne", "Dubai", "Mumbai", "London"],
    "answer": "Dubai"
  },
  {
    "question": "Who holds the record for the highest individual ODI score?",
    "options": [
      "Martin Guptill",
      "Rohit Sharma",
      "Chris Gayle",
      "Virender Sehwag"
    ],
    "answer": "Rohit Sharma"
  },
  {
    "question": "Who holds the record for the highest individual ODI score?",
    "options": [
      "Virender Sehwag",
      "Martin Guptill",
      "Rohit Sharma",
      "Chris Gayle"
    ],
    "answer": "Rohit Sharma"
  },
  {
    "question": "Which country won the first Cricket World Cup?",
    "options": ["England", "Australia", "West Indies", "India"],
    "answer": "West Indies"
  },
  {
    "question": "How many balls are bowled in one over?",
    "options": ["5", "6", "8", "4"],
    "answer": "6"
  },
  {
    "question": "What shape is a cricket ball?",
    "options": ["Round", "Oval", "Cylindrical", "Square"],
    "answer": "Round"
  },
  {
    "question": "What shape is a cricket ball?",
    "options": ["Round", "Cylindrical", "Square", "Oval"],
    "answer": "Round"
  },
  {
    "question": "Who holds the record for the highest individual ODI score?",
    "options": [
      "Martin Guptill",
      "Virender Sehwag",
      "Rohit Sharma",
      "Chris Gayle"
    ],
    "answer": "Rohit Sharma"
  },
  {
    "question": "What shape is a cricket ball?",
    "options": ["Square", "Cylindrical", "Round", "Oval"],
    "answer": "Round"
  },
  {
    "question": "Which player has taken the most Test wickets?",
    "options": [
      "Muttiah Muralitharan",
      "Shane Warne",
      "James Anderson",
      "Anil Kumble"
    ],
    "answer": "Muttiah Muralitharan"
  },
  {
    "question": "Who holds the record for the highest individual ODI score?",
    "options": [
      "Virender Sehwag",
      "Martin Guptill",
      "Chris Gayle",
      "Rohit Sharma"
    ],
    "answer": "Rohit Sharma"
  },
  {
    "question": "What shape is a cricket ball?",
    "options": ["Oval", "Square", "Round", "Cylindrical"],
    "answer": "Round"
  },
  {
    "question": "Who holds the record for the highest individual ODI score?",
    "options": [
      "Martin Guptill",
      "Chris Gayle",
      "Virender Sehwag",
      "Rohit Sharma"
    ],
    "answer": "Rohit Sharma"
  },
  {
    "question": "What shape is a cricket ball?",
    "options": ["Cylindrical", "Oval", "Round", "Square"],
    "answer": "Round"
  },
  {
    "question": "Who holds the record for the highest individual ODI score?",
    "options": [
      "Virender Sehwag",
      "Chris Gayle",
      "Rohit Sharma",
      "Martin Guptill"
    ],
    "answer": "Rohit Sharma"
  },
  {
    "question": "Which country won the first Cricket World Cup?",
    "options": ["India", "West Indies", "England", "Australia"],
    "answer": "West Indies"
  },
  {
    "question": "What shape is a cricket ball?",
    "options": ["Cylindrical", "Square", "Round", "Oval"],
    "answer": "Round"
  },
  {
    "question": "What shape is a cricket ball?",
    "options": ["Cylindrical", "Oval", "Square", "Round"],
    "answer": "Round"
  },
  {
    "question": "Which player has taken the most Test wickets?",
    "options": [
      "Muttiah Muralitharan",
      "Shane Warne",
      "James Anderson",
      "Anil Kumble"
    ],
    "answer": "Muttiah Muralitharan"
  },
  {
    "question": "What shape is a cricket ball?",
    "options": ["Square", "Round", "Cylindrical", "Oval"],
    "answer": "Round"
  },
  {
    "question": "Who holds the record for the highest individual ODI score?",
    "options": [
      "Virender Sehwag",
      "Rohit Sharma",
      "Martin Guptill",
      "Chris Gayle"
    ],
    "answer": "Rohit Sharma"
  },
  {
    "question": "Where is the ICC headquarters located?",
    "options": ["Mumbai", "Dubai", "London", "Melbourne"],
    "answer": "Dubai"
  },
  {
    "question": "Where is the ICC headquarters located?",
    "options": ["Melbourne", "Dubai", "Mumbai", "London"],
    "answer": "Dubai"
  },
  {
    "question": "What shape is a cricket ball?",
    "options": ["Oval", "Square", "Cylindrical", "Round"],
    "answer": "Round"
  },
  {
    "question": "Who is known as the 'God of Cricket'?",
    "options": [
      "Brian Lara",
      "Sachin Tendulkar",
      "Ricky Ponting",
      "Virat Kohli"
    ],
    "answer": "Sachin Tendulkar"
  },
  {
    "question": "Where is the ICC headquarters located?",
    "options": ["Dubai", "Melbourne", "London", "Mumbai"],
    "answer": "Dubai"
  },
  {
    "question": "Which country won the first Cricket World Cup?",
    "options": ["Australia", "England", "India", "West Indies"],
    "answer": "West Indies"
  },
  {
    "question": "Which player has taken the most Test wickets?",
    "options": [
      "Anil Kumble",
      "Shane Warne",
      "James Anderson",
      "Muttiah Muralitharan"
    ],
    "answer": "Muttiah Muralitharan"
  },
  {
    "question": "What shape is a cricket ball?",
    "options": ["Square", "Cylindrical", "Oval", "Round"],
    "answer": "Round"
  },
  {
    "question": "Which player has taken the most Test wickets?",
    "options": [
      "Anil Kumble",
      "James Anderson",
      "Shane Warne",
      "Muttiah Muralitharan"
    ],
    "answer": "Muttiah Muralitharan"
  },
  {
    "question": "What shape is a cricket ball?",
    "options": ["Square", "Cylindrical", "Round", "Oval"],
    "answer": "Round"
  },
  {
    "question": "Which country won the first Cricket World Cup?",
    "options": ["Australia", "India", "England", "West Indies"],
    "answer": "West Indies"
  },
  {
    "question": "Who holds the record for the highest individual ODI score?",
    "options": [
      "Martin Guptill",
      "Chris Gayle",
      "Virender Sehwag",
      "Rohit Sharma"
    ],
    "answer": "Rohit Sharma"
  },
  {
    "question": "Which country won the first Cricket World Cup?",
    "options": ["India", "West Indies", "England", "Australia"],
    "answer": "West Indies"
  },
  {
    "question": "Who holds the record for the highest individual ODI score?",
    "options": [
      "Virender Sehwag",
      "Chris Gayle",
      "Rohit Sharma",
      "Martin Guptill"
    ],
    "answer": "Rohit Sharma"
  },
  {
    "question": "Which player has taken the most Test wickets?",
    "options": [
      "Anil Kumble",
      "James Anderson",
      "Shane Warne",
      "Muttiah Muralitharan"
    ],
    "answer": "Muttiah Muralitharan"
  },
  {
    "question": "Who holds the record for the highest individual ODI score?",
    "options": [
      "Chris Gayle",
      "Virender Sehwag",
      "Martin Guptill",
      "Rohit Sharma"
    ],
    "answer": "Rohit Sharma"
  },
  {
    "question": "Where is the ICC headquarters located?",
    "options": ["London", "Melbourne", "Mumbai", "Dubai"],
    "answer": "Dubai"
  },
  {
    "question": "Which country won the first Cricket World Cup?",
    "options": ["India", "Australia", "England", "West Indies"],
    "answer": "West Indies"
  },
  {
    "question": "Who holds the record for the highest individual ODI score?",
    "options": [
      "Martin Guptill",
      "Virender Sehwag",
      "Chris Gayle",
      "Rohit Sharma"
    ],
    "answer": "Rohit Sharma"
  },
  {
    "question": "Who holds the record for the highest individual ODI score?",
    "options": [
      "Chris Gayle",
      "Rohit Sharma",
      "Martin Guptill",
      "Virender Sehwag"
    ],
    "answer": "Rohit Sharma"
  },
  {
    "question": "Which country won the first Cricket World Cup?",
    "options": ["England", "India", "Australia", "West Indies"],
    "answer": "West Indies"
  },
  {
    "question": "What do you call scoring 100 runs in an innings?",
    "options": ["Century", "Milestone", "Tonner", "Double"],
    "answer": "Century"
  },
  {
    "question": "Which player has taken the most Test wickets?",
    "options": [
      "Shane Warne",
      "James Anderson",
      "Muttiah Muralitharan",
      "Anil Kumble"
    ],
    "answer": "Muttiah Muralitharan"
  },
  {
    "question": "Who holds the record for the highest individual ODI score?",
    "options": [
      "Martin Guptill",
      "Rohit Sharma",
      "Chris Gayle",
      "Virender Sehwag"
    ],
    "answer": "Rohit Sharma"
  },
  {
    "question": "Who holds the record for the highest individual ODI score?",
    "options": [
      "Rohit Sharma",
      "Virender Sehwag",
      "Martin Guptill",
      "Chris Gayle"
    ],
    "answer": "Rohit Sharma"
  },
  {
    "question": "Who holds the record for the highest individual ODI score?",
    "options": [
      "Chris Gayle",
      "Virender Sehwag",
      "Martin Guptill",
      "Rohit Sharma"
    ],
    "answer": "Rohit Sharma"
  },
  {
    "question": "Where is the ICC headquarters located?",
    "options": ["Dubai", "Mumbai", "Melbourne", "London"],
    "answer": "Dubai"
  },
  {
    "question": "Where is the ICC headquarters located?",
    "options": ["Melbourne", "Dubai", "London", "Mumbai"],
    "answer": "Dubai"
  },
  {
    "question": "Which country won the first Cricket World Cup?",
    "options": ["West Indies", "India", "England", "Australia"],
    "answer": "West Indies"
  },
  {
    "question": "Which country won the first Cricket World Cup?",
    "options": ["Australia", "India", "England", "West Indies"],
    "answer": "West Indies"
  },
  {
    "question": "Where is the ICC headquarters located?",
    "options": ["London", "Melbourne", "Dubai", "Mumbai"],
    "answer": "Dubai"
  },
  {
    "question": "Who holds the record for the highest individual ODI score?",
    "options": [
      "Chris Gayle",
      "Virender Sehwag",
      "Rohit Sharma",
      "Martin Guptill"
    ],
    "answer": "Rohit Sharma"
  },
  {
    "question": "Where is the ICC headquarters located?",
    "options": ["Dubai", "Melbourne", "London", "Mumbai"],
    "answer": "Dubai"
  },
  {
    "question": "Which country won the first Cricket World Cup?",
    "options": ["Australia", "India", "England", "West Indies"],
    "answer": "West Indies"
  },
  {
    "question": "What shape is a cricket ball?",
    "options": ["Square", "Oval", "Cylindrical", "Round"],
    "answer": "Round"
  },
  {
    "question": "Who holds the record for the highest individual ODI score?",
    "options": [
      "Rohit Sharma",
      "Chris Gayle",
      "Martin Guptill",
      "Virender Sehwag"
    ],
    "answer": "Rohit Sharma"
  },
  {
    "question": "Where is the ICC headquarters located?",
    "options": ["Melbourne", "Mumbai", "Dubai", "London"],
    "answer": "Dubai"
  },
  {
    "question": "How many players are there in a cricket team?",
    "options": ["10", "11", "12", "9"],
    "answer": "11"
  },
  {
    "question": "Where is the ICC headquarters located?",
    "options": ["London", "Dubai", "Mumbai", "Melbourne"],
    "answer": "Dubai"
  },
  {
    "question": "Who holds the record for the highest individual ODI score?",
    "options": [
      "Chris Gayle",
      "Rohit Sharma",
      "Virender Sehwag",
      "Martin Guptill"
    ],
    "answer": "Rohit Sharma"
  },
  {
    "question": "Where is the ICC headquarters located?",
    "options": ["Dubai", "Melbourne", "London", "Mumbai"],
    "answer": "Dubai"
  },
  {
    "question": "What shape is a cricket ball?",
    "options": ["Cylindrical", "Oval", "Square", "Round"],
    "answer": "Round"
  },
  {
    "question": "Which player has taken the most Test wickets?",
    "options": [
      "Muttiah Muralitharan",
      "Anil Kumble",
      "Shane Warne",
      "James Anderson"
    ],
    "answer": "Muttiah Muralitharan"
  },
  {
    "question": "Which player has taken the most Test wickets?",
    "options": [
      "Shane Warne",
      "Anil Kumble",
      "Muttiah Muralitharan",
      "James Anderson"
    ],
    "answer": "Muttiah Muralitharan"
  },
  {
    "question": "Where is the ICC headquarters located?",
    "options": ["Mumbai", "London", "Dubai", "Melbourne"],
    "answer": "Dubai"
  },
  {
    "question": "Who holds the record for the highest individual ODI score?",
    "options": [
      "Virender Sehwag",
      "Rohit Sharma",
      "Martin Guptill",
      "Chris Gayle"
    ],
    "answer": "Rohit Sharma"
  },
  {
    "question": "Which player has taken the most Test wickets?",
    "options": [
      "Shane Warne",
      "Anil Kumble",
      "James Anderson",
      "Muttiah Muralitharan"
    ],
    "answer": "Muttiah Muralitharan"
  },
  {
    "question": "Which player has taken the most Test wickets?",
    "options": [
      "Muttiah Muralitharan",
      "Anil Kumble",
      "Shane Warne",
      "James Anderson"
    ],
    "answer": "Muttiah Muralitharan"
  },
  {
    "question": "Which country won the first Cricket World Cup?",
    "options": ["West Indies", "England", "India", "Australia"],
    "answer": "West Indies"
  },
  {
    "question": "Which player has taken the most Test wickets?",
    "options": [
      "James Anderson",
      "Shane Warne",
      "Anil Kumble",
      "Muttiah Muralitharan"
    ],
    "answer": "Muttiah Muralitharan"
  }
]
